odoo/addons/website_sale_partner_firstname/README.rst
odoo/addons/website_sale_partner_firstname/__init__.py
odoo/addons/website_sale_partner_firstname/__manifest__.py
odoo/addons/website_sale_partner_firstname/controllers/__init__.py
odoo/addons/website_sale_partner_firstname/controllers/main.py
odoo/addons/website_sale_partner_firstname/controllers/portal.py
odoo/addons/website_sale_partner_firstname/i18n/es.po
odoo/addons/website_sale_partner_firstname/models/__init__.py
odoo/addons/website_sale_partner_firstname/models/res_partner.py
odoo/addons/website_sale_partner_firstname/models/res_users.py
odoo/addons/website_sale_partner_firstname/static/description/icon.png
odoo/addons/website_sale_partner_firstname/views/auth_signup_login_templates.xml
odoo/addons/website_sale_partner_firstname/views/portal_templates.xml
odoo/addons/website_sale_partner_firstname/views/templates.xml
odoo_addon_website_sale_partner_firstname-15.0.1.0.0.4.dist-info/METADATA
odoo_addon_website_sale_partner_firstname-15.0.1.0.0.4.dist-info/WHEEL
odoo_addon_website_sale_partner_firstname-15.0.1.0.0.4.dist-info/top_level.txt
odoo_addon_website_sale_partner_firstname-15.0.1.0.0.4.dist-info/RECORD
